{
  "platform": "twitter",
  "scope": "daily",
  "date": "2026-07-06",
  "period_start": "2026-07-06",
  "period_end": "2026-07-06",
  "generated_at": "2026-07-07T07:08:17.247415+00:00",
  "images": [
    {
      "url": "https://raw.githubusercontent.com/pollinations/pollinations/news/social/news/daily/2026-07-06/images/twitter.jpg"
    }
  ],
  "text": "deduplicated and updated the tomdacat roblox app listing in our directory today. with 500+ apps in the ecosystem, entropy always wins eventually, but we can at least keep the floors swept."
}